odoo/addons/stock_inventory_virtual_location_change_qty_reason/README.rst
odoo/addons/stock_inventory_virtual_location_change_qty_reason/__init__.py
odoo/addons/stock_inventory_virtual_location_change_qty_reason/__manifest__.py
odoo/addons/stock_inventory_virtual_location_change_qty_reason/i18n/stock_inventory_virtual_location_change_qty_reason.pot
odoo/addons/stock_inventory_virtual_location_change_qty_reason/models/__init__.py
odoo/addons/stock_inventory_virtual_location_change_qty_reason/models/stock_inventory_line.py
odoo/addons/stock_inventory_virtual_location_change_qty_reason/models/stock_inventory_line_reason.py
odoo/addons/stock_inventory_virtual_location_change_qty_reason/readme/CONTRIBUTORS.rst
odoo/addons/stock_inventory_virtual_location_change_qty_reason/readme/DESCRIPTION.rst
odoo/addons/stock_inventory_virtual_location_change_qty_reason/static/description/icon.png
odoo/addons/stock_inventory_virtual_location_change_qty_reason/static/description/index.html
odoo/addons/stock_inventory_virtual_location_change_qty_reason/views/stock_inventory_line_reason_view.xml
odoo/addons/stock_inventory_virtual_location_change_qty_reason/wizard/__init__.py
odoo/addons/stock_inventory_virtual_location_change_qty_reason/wizard/stock_change_product_qty.py
odoo12_addon_stock_inventory_virtual_location_change_qty_reason-12.0.1.0.0.99.dev3.dist-info/METADATA
odoo12_addon_stock_inventory_virtual_location_change_qty_reason-12.0.1.0.0.99.dev3.dist-info/WHEEL
odoo12_addon_stock_inventory_virtual_location_change_qty_reason-12.0.1.0.0.99.dev3.dist-info/top_level.txt
odoo12_addon_stock_inventory_virtual_location_change_qty_reason-12.0.1.0.0.99.dev3.dist-info/RECORD
